.gitignore
README.txt
setup.py
js/__init__.py
js.rickshaw.egg-info/PKG-INFO
js.rickshaw.egg-info/SOURCES.txt
js.rickshaw.egg-info/dependency_links.txt
js.rickshaw.egg-info/entry_points.txt
js.rickshaw.egg-info/namespace_packages.txt
js.rickshaw.egg-info/not-zip-safe
js.rickshaw.egg-info/requires.txt
js.rickshaw.egg-info/top_level.txt
js/rickshaw/__init__.py
js/rickshaw/resources/rickshaw.css
js/rickshaw/resources/rickshaw.js
js/rickshaw/resources/rickshaw.min.css
js/rickshaw/resources/rickshaw.min.js