Metadata-Version: 1.0
Name: js.rickshaw
Version: 1.1.2
Summary: Fanstatic package for Rickshaw
Home-page: http://github.com/mgood/js.rickshaw/
Author: Matt Good
Author-email: matt@matt-good.net
License: BSD
Platform: any
